{
  "products": [
    {
      "id": 1,
      "name": "sanpham 1 122222",
      "price": 200,
      "description": "dat dadsdasjdsabbsbsbsbbsbskajndmnsdmsdnsb"
    },
    {
      "name": "1231111000000CCCCCCCCCCCCCCCCCCC",
      "price": "0213",
      "image": "",
      "description": "",
      "id": 4
    },
    {
      "name": "12312212222",
      "price": "0213",
      "image": "",
      "description": "",
      "id": 5
    },
    {
      "name": "123",
      "price": "0213",
      "image": "",
      "description": "",
      "id": 6
    },
    {
      "name": "123",
      "price": "0213",
      "image": "",
      "description": "",
      "id": 7
    },
    {
      "name": "123",
      "price": "0213",
      "image": "",
      "description": "",
      "id": 8
    },
    {
      "name": "123",
      "price": "0213",
      "image": "",
      "description": "",
      "id": 9
    },
    {
      "name": "123",
      "price": "0213",
      "image": "",
      "description": "",
      "id": 10
    },
    {
      "name": "123",
      "price": "0213",
      "image": "",
      "description": "",
      "id": 11
    },
    {
      "name": "123",
      "price": "0213",
      "image": "",
      "description": "",
      "id": 12
    },
    {
      "name": "123",
      "price": "0213",
      "image": "",
      "description": "",
      "id": 13
    },
    {
      "email": "datkidonguyen2003@gmail.com",
      "password": "datpro111",
      "name": "0528565307",
      "id": 14
    },
    {
      "email": "datkidonguyen2003@gmail.com",
      "password": "datpro111",
      "id": 15
    },
    {
      "name": "dat123",
      "price": "0111",
      "image": "",
      "description": "",
      "id": 16
    },
    {
      "email": "datkidonguyen2003@gmail.com",
      "password": "datpro111",
      "id": 17
    },
    {
      "email": "datkidonguyen2003@gmail.com",
      "password": "datpro111",
      "id": 18
    }
  ],
  "users": [
    {
      "email": "datkidonguyen2003@gmail.com",
      "password": "$2a$10$xlHjtW57HJytW51aieIDs.lULH/jtSoKJ98y8j4D7R668R/EoQ0UK",
      "id": 1
    }
  ]
}